rtl/tx/deserializer.sv
/*
*
* deserializer 4 bytes to 32 bit module
*
*/

module deserializer (

    input   logic               clk,
    input   logic               rst_n,
    input   logic               Cin,
    input   logic   [7 : 0]     Din,

    output  logic               Done,
    output  logic   [31 : 0]    Dout

);

logic [31 : 0] tmp;
logic [1 : 0] cnt;
logic sending;

always_ff @(posedge clk) begin
    Done <= 'b0;
    if (!rst_n) begin
        tmp <= 'b0;
        cnt <= 'b0;
        Done <= 'b0;
        sending <= 'b0;

    end else if (Cin) begin 
        tmp[7 : 0] <= Din;
        cnt <= 'b0;
        sending <= 'b1;
        Done = 'b0;
    end

    else if (sending) begin 
        tmp <= (tmp << 8);
        tmp[7 : 0] <= Din;
        cnt <= cnt + 'b1;

        if (cnt == 2'b11) begin
            Done <= 'b1;
            sending <= 'b0;
        end
    end
end

assign Dout = (sending) ? 'b0 : tmp;

endmodule

rtl/tx/serializer.sv
/*
*
* Serializer 32 to 4 bytes module
*
*/

module serializer(

    input   logic               clk,
    input   logic               rst_n,
    input   logic               Cin,
    input   logic   [31 : 0]    Din,

    output  logic   [7 : 0]     Dout,
    output  logic               Done

);

logic [31 : 0] tmp;
logic [1 : 0] cnt;
logic sending;

always_ff @(posedge clk) begin

    if (!rst_n) begin
        tmp <= 'b0;
        cnt <= 'b0;
        Done <= 'b0;
        sending <= 'b0;

    end else begin 
    if (cnt == 'b0) Done = 'b0;
    if (Cin) begin 
        tmp <= Din;
        cnt <= 'b0;
        sending <= 'b1;
        Done = 'b0;
    end

    else if (sending) begin 
        tmp <= (tmp << 8);
        cnt <= cnt + 'b1;

        if (cnt == 'b11) begin
            Done = 'b1;
            sending = 'b0;
            end
        end
    end
end


assign Dout = tmp[31 : 24];


endmodule

rtl/tx/serdes.sv
/*
*
*   Serializer -> deserializer loop for simulation
*
*/


module serdes (
    
    input   logic               clk,
    input   logic               rst_n,
    input   logic               Cin,
    input   logic   [31 : 0]    Din,

    output  logic   [31 : 0]    Dout,
    output  logic               Done

);

logic [7 : 0]Dout_ser;
logic Done_ser;

serializer serializer_inst (
    
    .clk(clk),
    .rst_n(rst_n),
    .Cin(Cin),
    .Din(Din),

    .Dout(Dout_ser),
    .Done(Done_ser)
 
);

deserializer deserializer_inst (
    
    .clk(clk),
    .rst_n(rst_n),
    .Cin(Cin),
    .Din(Dout_ser),

    .Dout(Dout),
    .Done(Done)
 
);


endmodule

sim/tb/tb_serdes.sv
`timescale 1ns/1ps

module tb_serdes();

logic clk;
logic rst_n;
logic Cin;
logic [31 : 0] Din;

logic [31 : 0] Dout;
logic Done;

serdes dut (
    
    .clk(clk),
    .rst_n(rst_n),
    .Cin(Cin),
    .Din(Din),

    .Dout(Dout),
    .Done(Done)
 
);


initial begin
    clk = 'b0;
    rst_n = 'b0;
    Cin = 'b0;
end

always begin
    #10 clk = ~clk;
end

initial begin
    
    $display("Starting test...");
    Din = 32'hDEADBEEF;

    #20;
    rst_n = ~rst_n;
   
    #10 Cin = 'b1;
    #10 Cin = 'b0;

    #500;

    $finish;
end

initial begin
    $dumpfile("serdes.vcd");
    $dumpvars(0, tb_serdes);
end

endmodule

sim/scripts/serdes.vcd
$date
	Thu May 08 20:04:53 2025
$end
$version
	ModelSim Version 2020.4
$end
$timescale
	1ns
$end

$scope module tb_serdes $end
$var reg 1 ! clk $end
$var reg 1 " rst_n $end
$var reg 1 # Cin $end
$var reg 32 $ Din [31:0] $end
$var reg 32 % Dout [31:0] $end
$var reg 1 & Done $end

$scope module dut $end
$var wire 1 ' clk $end
$var wire 1 ( rst_n $end
$var wire 1 ) Cin $end
$var wire 1 * Din [31] $end
$var wire 1 + Din [30] $end
$var wire 1 , Din [29] $end
$var wire 1 - Din [28] $end
$var wire 1 . Din [27] $end
$var wire 1 / Din [26] $end
$var wire 1 0 Din [25] $end
$var wire 1 1 Din [24] $end
$var wire 1 2 Din [23] $end
$var wire 1 3 Din [22] $end
$var wire 1 4 Din [21] $end
$var wire 1 5 Din [20] $end
$var wire 1 6 Din [19] $end
$var wire 1 7 Din [18] $end
$var wire 1 8 Din [17] $end
$var wire 1 9 Din [16] $end
$var wire 1 : Din [15] $end
$var wire 1 ; Din [14] $end
$var wire 1 < Din [13] $end
$var wire 1 = Din [12] $end
$var wire 1 > Din [11] $end
$var wire 1 ? Din [10] $end
$var wire 1 @ Din [9] $end
$var wire 1 A Din [8] $end
$var wire 1 B Din [7] $end
$var wire 1 C Din [6] $end
$var wire 1 D Din [5] $end
$var wire 1 E Din [4] $end
$var wire 1 F Din [3] $end
$var wire 1 G Din [2] $end
$var wire 1 H Din [1] $end
$var wire 1 I Din [0] $end
$var reg 32 J Dout [31:0] $end
$var reg 1 K Done $end
$var reg 8 L Dout_ser [7:0] $end
$var reg 1 M Done_ser $end

$scope module serializer_inst $end
$var wire 1 ' clk $end
$var wire 1 ( rst_n $end
$var wire 1 ) Cin $end
$var wire 1 * Din [31] $end
$var wire 1 + Din [30] $end
$var wire 1 , Din [29] $end
$var wire 1 - Din [28] $end
$var wire 1 . Din [27] $end
$var wire 1 / Din [26] $end
$var wire 1 0 Din [25] $end
$var wire 1 1 Din [24] $end
$var wire 1 2 Din [23] $end
$var wire 1 3 Din [22] $end
$var wire 1 4 Din [21] $end
$var wire 1 5 Din [20] $end
$var wire 1 6 Din [19] $end
$var wire 1 7 Din [18] $end
$var wire 1 8 Din [17] $end
$var wire 1 9 Din [16] $end
$var wire 1 : Din [15] $end
$var wire 1 ; Din [14] $end
$var wire 1 < Din [13] $end
$var wire 1 = Din [12] $end
$var wire 1 > Din [11] $end
$var wire 1 ? Din [10] $end
$var wire 1 @ Din [9] $end
$var wire 1 A Din [8] $end
$var wire 1 B Din [7] $end
$var wire 1 C Din [6] $end
$var wire 1 D Din [5] $end
$var wire 1 E Din [4] $end
$var wire 1 F Din [3] $end
$var wire 1 G Din [2] $end
$var wire 1 H Din [1] $end
$var wire 1 I Din [0] $end
$var reg 8 N Dout [7:0] $end
$var reg 1 O Done $end
$var reg 32 P tmp [31:0] $end
$var reg 2 Q cnt [1:0] $end
$var reg 1 R sending $end
$upscope $end

$scope module deserializer_inst $end
$var wire 1 ' clk $end
$var wire 1 ( rst_n $end
$var wire 1 ) Cin $end
$var wire 1 S Din [7] $end
$var wire 1 T Din [6] $end
$var wire 1 U Din [5] $end
$var wire 1 V Din [4] $end
$var wire 1 W Din [3] $end
$var wire 1 X Din [2] $end
$var wire 1 Y Din [1] $end
$var wire 1 Z Din [0] $end
$var reg 1 [ Done $end
$var reg 32 \ Dout [31:0] $end
$var reg 32 ] tmp [31:0] $end
$var reg 2 ^ cnt [1:0] $end
$var reg 1 _ sending $end
$upscope $end
$upscope $end
$upscope $end
$enddefinitions $end
#0
$dumpvars
0!
0"
0#
b11011110101011011011111011101111 $
bx %
x&
bx J
xK
bx L
xM
bx N
xO
bx P
bx Q
xR
x[
bx \
bx ]
bx ^
x_
1I
1H
1G
1F
0E
1D
1C
1B
0A
1@
1?
1>
1=
1<
0;
1:
19
08
17
16
05
14
03
12
01
10
1/
1.
1-
0,
1+
1*
0)
0(
0'
xZ
xY
xX
xW
xV
xU
xT
xS
$end
#10
1!
1'
b0 P
b0 Q
0O
0R
b0 ]
b0 ^
0[
0_
0K
b0 \
0M
b0 N
b0 L
b0 J
0&
b0 %
0Z
0Y
0X
0W
0V
0U
0T
0S
#20
1"
0!
1(
0'
#30
1#
1!
1)
1'
1_
b11011110101011011011111011101111 P
1R
b11011110 N
b11011110 L
1Y
1X
1W
1V
1T
1S
#40
0#
0!
0)
0'
#50
1!
1'
b10101101101111101110111100000000 P
b1 Q
b11011110 ]
b1 ^
b10101101 N
b10101101 L
1Z
0Y
0V
1U
0T
#60
0!
0'
#70
1!
1'
b1101111000000000 ]
b1101111010101101 ]
b10 ^
b10111110111011110000000000000000 P
b10 Q
b10111110 N
b10111110 L
0Z
1Y
1V
#80
0!
0'
#90
1!
1'
b11101111000000000000000000000000 P
b11 Q
b110111101010110100000000 ]
b110111101010110110111110 ]
b11 ^
b11101111 N
b11101111 L
1Z
0V
1T
#100
0!
0'
#110
1!
1'
1[
0_
1O
0R
1M
b110111101010110110111110 \
1K
1&
b110111101010110110111110 J
b110111101010110110111110 %
b11011110101011011011111000000000 ]
b11011110101011011011111011101111 ]
b0 ^
b0 P
b0 Q
b0 N
b11011110101011011011111011101111 \
b11011110101011011011111011101111 J
b0 L
b11011110101011011011111011101111 %
0Z
0Y
0X
0W
0U
0T
0S
#120
0!
0'
#130
1!
1'
0O
0[
0K
0M
0&
